toycode/__init__.py
toycode/main.py
toycode-0.0.2.dist-info/METADATA
toycode-0.0.2.dist-info/WHEEL
toycode-0.0.2.dist-info/entry_points.txt
toycode-0.0.2.dist-info/licenses/LICENSE.txt
toycode-0.0.2.dist-info/RECORD
