Metadata-Version: 2.3
Name: toycode
Version: 0.0.2
Summary: A simple Toycode program.
Project-URL: Homepage, https://www.skibur.com
Project-URL: Documentation, https://www.skibur.org
Project-URL: Repository, https://github.com/skibur/toycodepy.git
Project-URL: Changelog, https://github.com/skibur/toycodepy/blob/master/CHANGELOG.md
Author: Juan Antonio Sauceda
Author-email: jasgordo@gmail.com
License: GPLv2
License-File: LICENSE.txt
Keywords: code,toy
Classifier: Development Status :: 4 - Beta
Classifier: Environment :: Console
Classifier: Intended Audience :: Developers
Classifier: License :: OSI Approved :: GNU General Public License v2 (GPLv2)
Classifier: Programming Language :: Python :: 3
Classifier: Topic :: Education :: Testing
Requires-Python: >=3.0
